{
  "snapshots": [
    {
      "snapshot_id": "sample-replay-1",
      "config_version": "2026-03-08.v1",
      "snapshot_schema_version": "1.0.0",
      "symbol": "BTCUSDT",
      "decision_time": "2026-03-08T12:05:00+00:00",
      "last_trade_price": 50000.0,
      "best_bid": 49999.5,
      "best_ask": 50000.5,
      "funding_rate": 0.0001,
      "open_interest": 1000000.0,
      "basis_bps": 4.5,
      "data_freshness_ms": 250,
      "feature_values": {
        "ret_rank_1h": 0.8,
        "ret_rank_4h": 0.78,
        "breakout_norm": 0.82,
        "ema_stack_score": 1.0,
        "vol_z_5m_norm": 0.7,
        "vol_z_1h_norm": 0.72,
        "taker_imbalance_norm": 0.69,
        "spread_bps_norm": 0.2,
        "probe_slippage_bps_norm": 0.25,
        "depth_10bps_norm": 0.86,
        "book_stability_norm": 0.9,
        "realized_vol_1h_norm": 0.3,
        "realized_vol_4h_norm": 0.28,
        "vol_shock_norm": 0.35,
        "funding_abs_percentile": 0.14,
        "oi_surge_percentile": 0.1,
        "basis_stretch_percentile": 0.18,
        "regime_alignment": 1.0,
        "trend_direction": 1,
        "trend_strength": 0.82,
        "volume_confirmation": 0.74,
        "liquidity_score": 0.86,
        "volatility_penalty": 0.28,
        "overheat_penalty": 0.14,
        "predictability_score": 0.0,
        "gross_expected_edge_bps": 24.0,
        "net_expected_edge_bps": 0.0,
        "estimated_round_trip_cost_bps": 10.0
      }
    },
    {
      "snapshot_id": "sample-replay-2",
      "config_version": "2026-03-08.v1",
      "snapshot_schema_version": "1.0.0",
      "symbol": "ETHUSDT",
      "decision_time": "2026-03-08T12:10:00+00:00",
      "last_trade_price": 3000.0,
      "best_bid": 2999.8,
      "best_ask": 3000.2,
      "funding_rate": 0.0002,
      "open_interest": 1200000.0,
      "basis_bps": 5.0,
      "data_freshness_ms": 300,
      "feature_values": {
        "ret_rank_1h": 0.78,
        "ret_rank_4h": 0.77,
        "breakout_norm": 0.8,
        "ema_stack_score": 1.0,
        "vol_z_5m_norm": 0.73,
        "vol_z_1h_norm": 0.7,
        "taker_imbalance_norm": 0.7,
        "spread_bps_norm": 0.25,
        "probe_slippage_bps_norm": 0.26,
        "depth_10bps_norm": 0.76,
        "book_stability_norm": 0.85,
        "realized_vol_1h_norm": 0.34,
        "realized_vol_4h_norm": 0.33,
        "vol_shock_norm": 0.35,
        "funding_abs_percentile": 0.9,
        "oi_surge_percentile": 0.7,
        "basis_stretch_percentile": 0.4,
        "regime_alignment": 1.0,
        "trend_direction": 1,
        "trend_strength": 0.81,
        "volume_confirmation": 0.72,
        "liquidity_score": 0.76,
        "volatility_penalty": 0.34,
        "overheat_penalty": 0.67,
        "predictability_score": 0.0,
        "gross_expected_edge_bps": 22.0,
        "net_expected_edge_bps": 0.0,
        "estimated_round_trip_cost_bps": 10.0
      }
    }
  ]
}
